reverse_engineering/analysis.py
reverse_engineering/pomdp.py
reverse_engineering/utils/analysis_utils.py
reverse_engineering/utils/utils.py
reverse_engineering/utils/variable_conversion.py
reverse_engineering_py-0.1.2.dist-info/LICENSE
reverse_engineering_py-0.1.2.dist-info/METADATA
reverse_engineering_py-0.1.2.dist-info/WHEEL
reverse_engineering_py-0.1.2.dist-info/top_level.txt
reverse_engineering_py-0.1.2.dist-info/RECORD
