Metadata-Version: 2.2
Name: reverse-engineering-py
Version: 0.1.2
Summary: Python implementation of reverse engineering neural networks
Author-email: Takuya Isomura <takuya.isomura@riken.jp>
Maintainer-email: Araya Research DX <araya-researchdx-service@araya.org>
License:                     GNU GENERAL PUBLIC LICENSE
Project-URL: Repository, https://github.com/takuyaisomura/reverse-engineering-py
Project-URL: Bug Tracker, https://github.com/takuyaisomura/reverse-engineering-py/issues
Classifier: Programming Language :: Python :: 3
Classifier: License :: OSI Approved :: GNU General Public License v3 (GPLv3)
Classifier: Operating System :: OS Independent
Classifier: Topic :: Scientific/Engineering
Requires-Python: >=3.9
License-File: LICENSE
Requires-Dist: numpy
Requires-Dist: scipy
Requires-Dist: matplotlib
Requires-Dist: tqdm
Provides-Extra: dev
Requires-Dist: pytest; extra == "dev"
